{
  "keepSubset": {
    "_comment": "Nand drops variables associated with a DEPEND_0 when it has no dependents with type 'data'. Except these.",
    "RBSPA_EFW-L2_E-SPINFIT-MGSE": "epoch_hsk",
    "RBSPB_EFW-L2_E-SPINFIT-MGSE": "epoch_hsk"
  },
  "omitVariables": {
    "ALOUETTE2_NEPROF_TOPS": ["numDataPoints"],
    "FA_ESA_L2_EEB": ["geom_factor", "gf_ind", "denergy_full", "data_quality", "nenergy", "energy_full", "valid", "nbins", "mode_ind", "domega"],
    "FA_ESA_L2_EES": ["geom_factor", "gf_ind", "denergy_full", "data_quality", "nenergy", "energy_full", "valid", "nbins", "mode_ind", "domega"],
    "FA_ESA_L2_IEB": ["geom_factor", "gf_ind", "denergy_full", "data_quality", "nenergy", "energy_full", "valid", "nbins", "data_audio", "mode_ind", "domega"],
    "FA_ESA_L2_IES": ["geom_factor", "gf_ind", "denergy_full", "data_quality", "nenergy", "energy_full", "valid", "nbins", "mode_ind", "domega"],
    "I1_NEPROF_TOPS": ["numDataPoints"],
    "I2_NEPROF_TOPS": ["numDataPoints"],
    "ISS_DOSANL_TEPC": ["FLAG", "LOCATION"],
    "VOYAGER1_48S_MAG": ["magStatus", "magCommand", "num9_6_averages"],
    "VOYAGER2_48S_MAG": ["magStatus", "magCommand", "num9_6_averages"],
    "VOYAGER1_2S_MAG": ["RMSB1", "RMSB2", "B1", "F1", "RMSB3", "F2", "numDetailPoints", "B2", "B3"],
    "VOYAGER2_2S_MAG": ["RMSB1", "RMSB2", "B1", "F1", "RMSB3", "F2", "numDetailPoints", "B2", "B3"],
    "WI_EM_3DP": ["VALID", "GAP"],
    "WI_PM_3DP": ["VALID", "E_RANGE", "GAP"]
  },
  "omitSubset": {
    "AEROCUBE-6-A_DOSIMETER_L2": "Epoch_10Hz",
    "AEROCUBE-6-B_DOSIMETER_L2": "Epoch_10Hz",
    "ELA_L1_STATE_PRED": "ela_att_time",
    "ELB_L1_STATE_PRED": "elb_att_time",
    "FA_ESA_L2_EEB": "orbit_number_epoch",
    "FA_ESA_L2_EES": "orbit_number_epoch",
    "FA_ESA_L2_IEB": "orbit_number_epoch",
    "FA_ESA_L2_IES": "orbit_number_epoch",
    "GE_EDA12SEC_LEP": "scan_code",
    "PO_LEVEL1_UVI": "EPOCH_51",
    "PSP_FLD_L2_DFB_DBM_SCM": "epoch_psp_fld_l2_dfb_dbm_scmlg",
    "VOYAGER1_2S_MAG": "Epoch",
    "VOYAGER2_2S_MAG": "Epoch"
  },
  "omitAll": {
    "ALOUETTE2_AV_QUI": null,
    "APOLLO12_SWS_1HR": null,
    "APOLLO12_SWS_28S": null,
    "APOLLO15_SWS_1HR": null,
    "APOLLO15_SWS_28S": null,
    "C2_PP_EFW": null,
    "C3_PP_EFW": null,
    "C4_PP_EFW": null,
    "C2_WAVEFORM_WBD_BM2": null,
    "C3_WAVEFORM_WBD_BM2": null,
    "C4_WAVEFORM_WBD_BM2": null,
    "CL_SP_AUX": null,
    "ERG_LEPE_L2_OMNIFLUX": null,
    "ERG_PWE_EFD_L2_E_SPIN": null,
    "FAST_OR_SSC": null,
    "FAST_TEAMS_PA_L2": null,
    "DAWN_HELIO1DAY_POSITION": null,
    "FORMOSAT5_AIP_IDN": null,
    "DN_MAGN-L2-HIRES_G17": null,
    "DN_MAGN-L2-HIRES_G16": null,
    "DN_MAGN-L2-HIRES_G15": null,
    "DN_MAGN-L2-HIRES_G14": null,
    "DN_MAGN-L2-HIRES_G13": null,
    "DN_MAGN-L2-HIRES_G12": null,
    "DN_MAGN-L2-HIRES_G11": null,
    "DN_MAGN-L2-HIRES_G10": null,
    "DN_MAGN-L2-HIRES_G09": null,
    "DN_MAGN-L2-HIRES_G08": null,
    "GE_K0_LEP": null,
    "GPS_RF_LANL-VTEC-1HR": null,
    "GOES9_EPHEMERIS_SSC": null,
    "GOES8_EPHEMERIS_SSC": null,
    "ICON_L2-1_MIGHTI-B_LOS-WIND-GREEN": null,
    "ICON_L2-1_MIGHTI-A_LOS-WIND-RED": null,
    "ICON_L2-1_MIGHTI-B_LOS-WIND-RED": null,
    "ICON_L2-2_MIGHTI_VECTOR-WIND-GREEN": null,
    "ICON_L2-2_MIGHTI_VECTOR-WIND-RED": null,
    "ICON_L2-3_MIGHTI-A_TEMPERATURE": null,
    "ICON_L2-3_MIGHTI-B_TEMPERATURE": null,
    "ICON_L2-4_FUV_DAY": null,
    "ICON_L2-5_FUV_NIGHT": null,
    "ICON_L2-6_EUV": null,
    "ICON_L2-7_IVM-A": null,
    "ICON_L2-7_IVM-B": null,
    "I1_AV2_OTT": null,
    "I1_AV2_ULA": null,
    "I1_AV_ODG": null,
    "I1_AV_ORR": null,
    "I1_AV_RES": null,
    "I1_AV_ULA": null,
    "I2_AV_ODG": null,
    "I2_AV_RES": null,
    "I2_AV_SNT": null,
    "I2_AV_SYO": null,
    "MSL_RAD_OBS-L2": null,
    "MSL_RAD_OBS-L1": null,
    "MVN_STA_L2_DA-1R64E": null,
    "MMS4_EDI_BRST_L2_AMB": null,
    "MMS4_FPI_BRST_L2_DES-MOMS": null,
    "MMS4_FPI_BRST_L2_DES-PARTMOMS": null,
    "PMC-TURBO_L1_BOLIDE_VBC": null,
    "PO_H2_TIM": null,
    "RBSP-A-RBSPICE_LEV-3-PAP_TOFXEHE": null,
    "RBSP-B-RBSPICE_LEV-3-PAP_TOFXEHE": null,
    "RBSP-A-RBSPICE_LEV-3-PAP_TOFXEO": null,
    "RBSP-B-RBSPICE_LEV-3-PAP_TOFXEO": null,
    "RBSP-A_MAGNETOMETER_HIRES-GEI_EMFISIS-L3": null,
    "RBSP-B_MAGNETOMETER_HIRES-GEI_EMFISIS-L3": null,
    "RBSP-A_MAGNETOMETER_HIRES-GEO_EMFISIS-L3": null,
    "RBSP-B_MAGNETOMETER_HIRES-GEO_EMFISIS-L3": null,
    "RBSP-A_MAGNETOMETER_HIRES-GSE_EMFISIS-L3": null,
    "RBSP-B_MAGNETOMETER_HIRES-GSE_EMFISIS-L3": null,
    "RBSP-A_MAGNETOMETER_HIRES-GSM_EMFISIS-L3": null,
    "RBSP-B_MAGNETOMETER_HIRES-GSM_EMFISIS-L3": null,
    "RBSP-A_MAGNETOMETER_HIRES-SM_EMFISIS-L3": null,
    "RBSP-B_MAGNETOMETER_HIRES-SM_EMFISIS-L3": null,
    "RBSP-A_MAGNETOMETER_UVW_EMFISIS-L2": null,
    "RBSP-B_MAGNETOMETER_UVW_EMFISIS-L2": null,
    "RBSP-A_HFR-SPECTRA-MERGED_EMFISIS-L2": null,
    "SOLO_L2_SWA-EAS1-SS-PSD": null,
    "SOLO_L2_SWA-EAS1-SS-DNF": null,
    "SOLO_L2_SWA-EAS1-SS-DEF": null,
    "TIMED_WINDVECTORSNCAR_TIDI": null,
    "TWINS2_AT_DEF": null
  }
}